nlcli/__init__.py
nlcli-0.1.2.dist-info/WHEEL
nlcli-0.1.2.dist-info/METADATA
nlcli-0.1.2.dist-info/RECORD
