Metadata-Version: 2.1
Name: nlcli
Version: 0.1.2
Summary: 
License: MIT
Author: João Rafael
Author-email: joaoraf@me.com
Requires-Python: >=3,<4
Classifier: License :: OSI Approved :: MIT License
Classifier: Programming Language :: Python :: 3
Classifier: Programming Language :: Python :: 3.4
Classifier: Programming Language :: Python :: 3.5
Classifier: Programming Language :: Python :: 3.6
Classifier: Programming Language :: Python :: 3.7
Classifier: Programming Language :: Python :: 3.8
Classifier: Programming Language :: Python :: 3.9
Requires-Dist: fann2 (==1.0.7)
Requires-Dist: padatious
